{"items": [{"name": "gaiagaiamilkyway", "new": false, "score": "2411.83", "datet": "2022-12-7 21:2:25 UTC"}, {"name": "gaiagaiazoombright", "new": false, "score": "11401.9", "datet": "2022-12-7 20:55:6 UTC"}, {"name": "newhorizonsNewHorizionsModel", "new": false, "score": "3435.04", "datet": "2022-12-7 21:9:59 UTC"}, {"name": "defaultEarth", "new": false, "score": "2626.93", "datet": "2022-12-7 21:27:16 UTC"}, {"name": "osirisrexosirisrexmodel", "new": false, "score": "3494.2", "datet": "2022-12-7 20:39:43 UTC"}, {"name": "marsinsightparachute", "new": false, "score": "16618.7", "datet": "2022-11-2 20:59:43 UTC"}, {"name": "apollo11landing", "new": false, "score": "6017.83", "datet": "2022-12-7 20:43:44 UTC"}, {"name": "newhorizonsNewHorizonsPlutoProjection", "new": false, "score": "856.767", "datet": "2022-12-7 21:15:44 UTC"}, {"name": "osirisrexosirisrexprojection", "new": false, "score": "9535.4", "datet": "2022-12-7 20:35:58 UTC"}, {"name": "apollo11landingsite", "new": false, "score": "10028.4", "datet": "2022-12-7 20:53:40 UTC"}, {"name": "gaiagaiazoom", "new": false, "score": "2143.88", "datet": "2022-12-7 21:6:26 UTC"}, {"name": "marsinsightousideatmosphere", "new": false, "score": "16712.4", "datet": "2022-12-7 20:28:59 UTC"}, {"name": "gaiagaiadefaultstart", "new": false, "score": "5719.49", "datet": "2022-12-7 21:5:6 UTC"}, {"name": "marsinsightlanded", "new": false, "score": "15186.1", "datet": "2022-12-7 20:30:50 UTC"}, {"name": "junojunomodel", "new": false, "score": "2471.82", "datet": "2022-12-7 21:18:29 UTC"}, {"name": "apollo17landingsite", "new": false, "score": "13982.5", "datet": "2022-12-7 20:49:33 UTC"}, {"name": "gaiagaiatime100000000000000", "new": false, "score": "1179.06", "datet": "2022-12-7 20:58:50 UTC"}, {"name": "gaiagaiatime10000000000000", "new": false, "score": "1006.54", "datet": "2022-12-7 21:3:47 UTC"}, {"name": "voyagervoyagers2020", "new": false, "score": "2920.78", "datet": "2022-12-7 21:38:25 UTC"}, {"name": "defaultMoonSurface", "new": false, "score": "1908.13", "datet": "2022-12-7 21:24:25 UTC"}, {"name": "apollopreearthrise", "new": false, "score": "16051.8", "datet": "2022-12-7 20:51:49 UTC"}, {"name": "marsinsightinsideatmosphere", "new": false, "score": "15296.9", "datet": "2022-11-2 20:57:53 UTC"}, {"name": "rosettarosettaprojection", "new": false, "score": "1109.27", "datet": "2022-10-28 23:41:21 UTC"}, {"name": "defaultSolarSystem", "new": false, "score": "5127.74", "datet": "2022-12-7 21:25:44 UTC"}, {"name": "junojunotrailfull", "new": false, "score": "4294.83", "datet": "2022-12-7 21:17:10 UTC"}, {"name": "defaultMarsHiRISE", "new": false, "score": "3732.42", "datet": "2022-12-7 21:22:28 UTC"}, {"name": "apollo11orbits", "new": false, "score": "8903.33", "datet": "2022-12-7 20:45:32 UTC"}, {"name": "voyagervoyager1model", "new": false, "score": "9903.85", "datet": "2022-12-7 21:37:2 UTC"}, {"name": "rosettarosettamodel", "new": false, "score": "12134.1", "datet": "2022-12-7 21:30:52 UTC"}]}